kimrec/__init__.py
kimrec/errors.py
kimrec/eval.py
kimrec/input_utils.py
kimrec/kimrec.py
kimrec/loss_graphs.py
kimrec/prediction_graphs.py
kimrec/recommendation_graphs.py
kimrec/representation_graphs.py
kimrec/session_management.py
kimrec/tensorrec.py
kimrec/util.py
tensorrec/__init__.py
tensorrec/errors.py
tensorrec/eval.py
tensorrec/input_utils.py
tensorrec/loss_graphs.py
tensorrec/prediction_graphs.py
tensorrec/recommendation_graphs.py
tensorrec/representation_graphs.py
tensorrec/session_management.py
tensorrec/tensorrec.py
tensorrec/util.py
kimrec-0.26.5.dist-info/METADATA
kimrec-0.26.5.dist-info/WHEEL
kimrec-0.26.5.dist-info/top_level.txt
kimrec-0.26.5.dist-info/RECORD
