Metadata-Version: 2.1
Name: kimrec
Version: 0.26.5
Summary: A TensorFlow recommendation algorithm and framework <Tensorrec> in Python modified by Hyeonjae Kim
Home-page: https://github.com/journey101/kimrec-for-tensorflow-recommendation
Author: Hyeonjae Kim
Author-email: hyeonjae.gim@gmail.com
License: UNKNOWN
Keywords: machine-learning,tensorflow,recommendation-system,python,recommender-system
Platform: UNKNOWN
Requires-Dist: numpy (>=1.14.1)
Requires-Dist: scipy (>=0.19.1)
Requires-Dist: six (==1.11.0)
Requires-Dist: tensorflow (>=2.4.1)
